HLL.cpython-312-x86_64-linux-gnu.so
hll-2.4.0.dist-info/METADATA
hll-2.4.0.dist-info/WHEEL
hll-2.4.0.dist-info/top_level.txt
hll-2.4.0.dist-info/RECORD
hll-2.4.0.dist-info/licenses/LICENSE
