Metadata-Version: 2.4
Name: HLL
Version: 2.4.0
Summary: Fast HyperLogLog for Python
Home-page: https://github.com/ascv/HyperLogLog
Author: Joshua Andersen
Author-email: josh.h.andersen@gmail.com
Maintainer: Joshua Andersen
License: MIT
Keywords: algorithm,approximate counting,big data,big data,cardinality,cardinality estimate,counting,data analysis,data processing,data science,data sketching,efficient computation,estimating cardinality,fast,frequency estimation,hyper log log,hyper loglog,hyperloglog,large-scale data,log log,loglog,memory efficient,probability estimate,probability sketch,probablistic counting,probablistic data structures,real-time analytics,scalable,set cardinality,set operations,sketch,statistical analysis,str
Requires-Python: >=3.6, <4
License-File: LICENSE
Dynamic: author
Dynamic: author-email
Dynamic: description
Dynamic: description-content-type
Dynamic: home-page
Dynamic: keywords
Dynamic: license
Dynamic: license-file
Dynamic: maintainer
Dynamic: requires-python
Dynamic: summary
